airclerk/__init__.py
airclerk/main.py
airclerk-0.1.0.dist-info/WHEEL
airclerk-0.1.0.dist-info/METADATA
airclerk-0.1.0.dist-info/RECORD
