Metadata-Version: 2.3
Name: AirClerk
Version: 0.1.0
Summary: Air + Clerk for user management.
Author: Daniel Roy Greenfeld, Audrey Roy Greenfeld
Author-email: Daniel Roy Greenfeld <daniel@feldroy.com>, Audrey Roy Greenfeld <audrey@feldroy.com>
Requires-Dist: air>=0.40.0
Requires-Dist: clerk-backend-api>=3.3.1
Requires-Dist: fastapi[standard]>=0.121.0
Requires-Dist: httpx>=0.28.1
Requires-Dist: pydantic-settings>=2.11.0
Requires-Python: >=3.13
Project-URL: Homepage, https://github.com/feldroy/airclerk
Project-URL: Issues, https://github.com/feldroy/airclerk/issues
